setup.py
flask_awesomemongokit/__init__.py
flask_awesomemongokit/extension.py
flask_awesomemongokit/index.py
flask_awesomemongokit.egg-info/PKG-INFO
flask_awesomemongokit.egg-info/SOURCES.txt
flask_awesomemongokit.egg-info/dependency_links.txt
flask_awesomemongokit.egg-info/requires.txt
flask_awesomemongokit.egg-info/top_level.txt