Metadata-Version: 1.0
Name: flask-awesomemongokit
Version: 0.3.3
Summary: Sets up an extremely opinionated MongoKit environment in Flask, based selfishly on my own needs.
Home-page: https://github.com/angstwad/flask-awesomemongokit
Author: Paul Durivage
Author-email: pauldurivage+github@gmail.com
License: Apache License v2.0
Platform: UNKNOWN
